Metadata-Version: 2.1
Name: phykit
Version: 2.1.2
Home-page: https://github.com/jlsteenwyk/phykit
Author: Jacob L. Steenwyk
Author-email: jlsteenwyk@gmail.com
Classifier: Operating System :: OS Independent
Classifier: Intended Audience :: Science/Research
Classifier: Programming Language :: Python
Classifier: Programming Language :: Python :: 3.9
Classifier: Programming Language :: Python :: 3.10
Classifier: Programming Language :: Python :: 3.11
Classifier: Programming Language :: Python :: 3.12
Classifier: Programming Language :: Python :: 3.13
Classifier: Topic :: Scientific/Engineering
License-File: LICENSE.md
Requires-Dist: biopython>=1.82
Requires-Dist: numpy>=1.24.0
Requires-Dist: scipy>=1.11.3
Requires-Dist: scikit-learn>=1.4.2
Requires-Dist: cython
Requires-Dist: tqdm>=4.65.0
